{
  "boxes": [
    {
      "type": "polygon",
      "points": [
        [
          0.03333333333333333,
          0.7523809523809524
        ],
        [
          0.24285714285714285,
          0.5428571428571428
        ],
        [
          0.18571428571428572,
          0.5178571428571429
        ],
        [
          0,
          0.7238095238095238
        ]
      ],
      "color": "black"
    },
    {
      "type": "polygon",
      "points": [
        [
          0.5119331742243437,
          0.31216457960644006
        ],
        [
          0.5405727923627685,
          0.3354203935599284
        ],
        [
          0.6384248210023866,
          0.22093023255813954
        ],
        [
          0.6097852028639618,
          0.19499105545617174
        ]
      ],
      "color": "white"
    }
  ]
}